{
    "0": {
        "a": 4.438672,
        "b": 4.438672,
        "c": 6.03054834,
        "alpha": 111.59328752,
        "beta": 111.59328752,
        "gamma": 89.99999998999999,
        "comp": {
            "[0.0, 0.0, 0.0]": "Sr1",
            "[0.5, 0.5, 0.5]": "Sr1",
            "[0.0, 0.0, 0.37057000000000007]": "Ge1",
            "[0.5, 0.5, 0.12942999999999993]": "Ge1",
            "[0.5, 0.5, 0.8705700000000001]": "Ge1",
            "[0.0, 0.0, 0.6294299999999999]": "Ge1",
            "[0.0, 0.5, 0.25]": "Ag0.05 Pd0.95",
            "[0.5, 0.0, 0.25]": "Ag0.05 Pd0.95",
            "[0.5, 0.0, 0.75]": "Ag0.05 Pd0.95",
            "[0.0, 0.5, 0.75]": "Ag0.05 Pd0.95"
        },
        "target": 123.0
    },
    "1": {
        "a": 5.46409128,
        "b": 5.46409128,
        "c": 5.46409128,
        "alpha": 59.99999999999999,
        "beta": 59.99999999999999,
        "gamma": 59.99999999999999,
        "comp": {
            "[0.0, 0.5, 0.0]": "La0.9 Ce0.1",
            "[0.25, 0.75, 0.25]": "La0.9 Ce0.1",
            "[0.0, 0.0, 0.5]": "La0.9 Ce0.1",
            "[0.25, 0.25, 0.75]": "La0.9 Ce0.1",
            "[0.5, 0.5, 0.5]": "La0.9 Ce0.1",
            "[0.75, 0.75, 0.75]": "La0.9 Ce0.1",
            "[0.5, 0.0, 0.0]": "La0.9 Ce0.1",
            "[0.75, 0.25, 0.25]": "La0.9 Ce0.1",
            "[0.875, 0.625, 0.375]": "Ru1",
            "[0.125, 0.625, 0.625]": "Ru1",
            "[0.125, 0.375, 0.375]": "Ru1",
            "[0.875, 0.375, 0.625]": "Ru1",
            "[0.875, 0.125, 0.875]": "Ru1",
            "[0.125, 0.125, 0.125]": "Ru1",
            "[0.125, 0.875, 0.875]": "Ru1",
            "[0.875, 0.875, 0.125]": "Ru1",
            "[0.375, 0.625, 0.875]": "Ru1",
            "[0.625, 0.625, 0.125]": "Ru1",
            "[0.625, 0.375, 0.875]": "Ru1",
            "[0.375, 0.375, 0.125]": "Ru1",
            "[0.375, 0.125, 0.375]": "Ru1",
            "[0.625, 0.125, 0.625]": "Ru1",
            "[0.625, 0.875, 0.375]": "Ru1",
            "[0.375, 0.875, 0.625]": "Ru1"
        },
        "target": 321.0
    }
}